metarclone/__init__.py
metarclone/checksum.py
metarclone/cli.py
metarclone/config.py
metarclone/download.py
metarclone/metadata.py
metarclone/rclone.py
metarclone/upload.py
metarclone/utils.py
metarclone-0.0.1.dev2.dist-info/METADATA
metarclone-0.0.1.dev2.dist-info/WHEEL
metarclone-0.0.1.dev2.dist-info/entry_points.txt
metarclone-0.0.1.dev2.dist-info/top_level.txt
metarclone-0.0.1.dev2.dist-info/RECORD
