Metadata-Version: 2.1
Name: metarclone
Version: 0.0.1.dev2
Summary: Metadata-preserving backup with small file merging using Rclone
Home-page: https://github.com/adrien1018/metarclone
Author: Adrien Wu
Author-email: adrien.sf.wu@gmail.com
Requires-Python: >=3.6
Requires-Dist: disjoint-set
